naosconnector.py
naosconnector-0.1.5.dist-info/METADATA
naosconnector-0.1.5.dist-info/WHEEL
naosconnector-0.1.5.dist-info/RECORD
