Metadata-Version: 2.3
Name: naosconnector
Version: 0.1.5
Summary: helper class to connect to a Naos platform
License: Commercial
Author: Nicolas Parment
Author-email: nparment@forsk.com
Requires-Python: >=3.9
Classifier: License :: Other/Proprietary License
Classifier: Programming Language :: Python :: 3
Classifier: Programming Language :: Python :: 3.9
Classifier: Programming Language :: Python :: 3.10
Classifier: Programming Language :: Python :: 3.11
Classifier: Programming Language :: Python :: 3.12
Classifier: Programming Language :: Python :: 3.13
Requires-Dist: requests (>=2.32.3,<3.0.0)
